CHANGELOG.md
LICENSE
MANIFEST.in
README.md
setup.cfg
setup.py
django_tegro_money/__init__.py
django_tegro_money/admin.py
django_tegro_money/apps.py
django_tegro_money/exceptions.py
django_tegro_money/loggers.py
django_tegro_money/models.py
django_tegro_money/settings.py
django_tegro_money/tegro_money.py
django_tegro_money/urls.py
django_tegro_money/utils.py
django_tegro_money/views.py
django_tegro_money.egg-info/PKG-INFO
django_tegro_money.egg-info/SOURCES.txt
django_tegro_money.egg-info/dependency_links.txt
django_tegro_money.egg-info/not-zip-safe
django_tegro_money.egg-info/requires.txt
django_tegro_money.egg-info/top_level.txt
django_tegro_money/migrations/0001_initial.py
django_tegro_money/migrations/__init__.py