Metadata-Version: 2.1
Name: django-tegro-money
Version: 0.1.0
Summary: Django Tegro.Money HTTP API Connector
Home-page: https://github.com/KotelnikovKP/django-tegro-money
Author: Konstantin Kotelnikov
Author-email: kotelnikov1302@gmail.com
License: MIT License
Keywords: tegro money api connector
Classifier: Development Status :: 4 - Beta
Classifier: Environment :: Web Environment
Classifier: Intended Audience :: Developers
Classifier: Topic :: Software Development :: Libraries :: Python Modules
Classifier: License :: OSI Approved :: MIT License
Classifier: Operating System :: OS Independent
Classifier: Programming Language :: Python
Classifier: Programming Language :: Python :: 3.8
Classifier: Programming Language :: Python :: 3.9
Classifier: Programming Language :: Python :: 3.10
Classifier: Programming Language :: Python :: 3.11
Classifier: Framework :: Django
Requires-Python: >=3.8
License-File: LICENSE
